django_gvar/__init__.py
django_gvar/_version.py
django_gvar/fields.py
django_gvar/forms.py
django_gvar/parser.py
django_gvar/testing.py
django_gvar-0.1.0a0.dist-info/LICENSE.md
django_gvar-0.1.0a0.dist-info/METADATA
django_gvar-0.1.0a0.dist-info/WHEEL
django_gvar-0.1.0a0.dist-info/top_level.txt
django_gvar-0.1.0a0.dist-info/RECORD
