Metadata-Version: 2.1
Name: django-gvar
Version: 0.1.0a0
Summary: Django extension which adds model fields to store multi-dimensional Gaussian random variables.
Home-page: https://github.com/callat-qcd/django-gvar
Author: @ckoerber
Author-email: software@ckoerber.com
License: UNKNOWN
Project-URL: Bug Reports, https://github.com/callat-qcd/django-gvar/issues
Project-URL: Source, https://github.com/callat-qcd/django-gvar
Project-URL: Documentation, https://django-gvar.readthedocs.io
Keywords: Database,Django,GVar,Statistics
Platform: UNKNOWN
Classifier: Development Status :: 3 - Alpha
Classifier: Intended Audience :: Science/Research
Classifier: Topic :: Database :: Database Engines/Servers
Classifier: Topic :: Database
Classifier: Topic :: Scientific/Engineering
Classifier: Intended Audience :: Science/Research
Classifier: Intended Audience :: Developers
Classifier: Operating System :: OS Independent
Classifier: Framework :: Django :: 3.1
Classifier: Programming Language :: Python :: 3.6
Classifier: Programming Language :: Python :: 3.7
Classifier: Programming Language :: Python :: 3.8
Classifier: License :: OSI Approved :: BSD License
Requires-Python: >=3.6
Requires-Dist: Django (==3.1a1)
Requires-Dist: numpy
Requires-Dist: gvar
Provides-Extra: dev
Requires-Dist: pytest ; extra == 'dev'
Requires-Dist: pytest-django ; extra == 'dev'
Requires-Dist: pytest-cov ; extra == 'dev'
Requires-Dist: black ; extra == 'dev'
Requires-Dist: flake8 ; extra == 'dev'
Requires-Dist: flake8-docstrings ; extra == 'dev'
Requires-Dist: mkdocs ; extra == 'dev'
